check_vat/__init__.py
check_vat-0.2.1.dist-info/LICENSE
check_vat-0.2.1.dist-info/METADATA
check_vat-0.2.1.dist-info/WHEEL
check_vat-0.2.1.dist-info/top_level.txt
check_vat-0.2.1.dist-info/RECORD
