Metadata-Version: 2.1
Name: check-vat
Version: 0.2.1
Summary: Checks if a given string is a valid (real, registered) European VAT ID
Home-page: https://github.com/tuergeist/check-vat
Author: Christoph Becker
Author-email: tuergeist@gmail.com
License: UNKNOWN
Platform: UNKNOWN
Classifier: Programming Language :: Python :: 3
Classifier: License :: OSI Approved :: MIT License
Classifier: Operating System :: OS Independent
